pkg1/__init__.py
pkg1/test.py
pkg2/__init__.py
pkg2/test.py
test_aa-0.0.1.dist-info/METADATA
test_aa-0.0.1.dist-info/WHEEL
test_aa-0.0.1.dist-info/top_level.txt
test_aa-0.0.1.dist-info/RECORD
