Metadata-Version: 2.1
Name: test-aa
Version: 0.0.1
Summary: kk
Author: me
Project-URL: homepage, https://github.com/pypa/sampleproject
Classifier: Programming Language :: Python :: 3
Classifier: License :: OSI Approved :: MIT License
Classifier: Operating System :: OS Independent
Requires-Python: >=3.11
